{
  "slug": "nuigurumi-suterarenai",
  "title": "ぬいぐるみが捨てられない…その気持ちは正常です｜罪悪感なく手放す5つの方法",
  "description": "ぬいぐるみが捨てられないのは、愛着や罪悪感が働く自然な心理です。捨てられない理由をやさしく解説し、供養・寄付・写真保存など罪悪感なく手放せる5つの方法を紹介します。生前整理・実家の片付けにも役立つ内容です。",
  "category": "mental",
  "tags": ["guilt-cannot-throw", "parent-stubborn"],
  "supervisor": "general",
  "journey_phase": "P2",
  "phase": "F2",
  "cluster": "品目別 処分・供養・買取",
  "note": "低競合ロングテール(競合2)。感情/供養。supervisor=general(生前整理アドバイザー=mental領域で正当)。差別化=生前整理・実家片付け文脈＋デス・クリーニング＋訪問買取注意(国民生活センター)。CV=/checklist・/guidebook。クラスタ相互リンクで/articles/jikka-jimai-guide(P1ハブ公開済)へ。非ピラー2000-3000字。"
}
