[
  {"prefId":"shizuoka","cityId":"shizuoka","cityName":"静岡市","prefName":"静岡県","mascot":null,"subsidy":{"hasSubsidy":true,"name":"静岡市老朽危険空き家除却補助金","maxAmount":"最大60万円（費用の1/2以内）※特定空家等は最大100万円","conditions":["昭和56年5月31日以前に建築された空き家","1年以上使用されていない住宅","市税（固定資産税等）を滞納していない","個人が所有している住宅であること","補助金交付決定後に着工すること"],"applicationPeriod":"令和7年度（予算がなくなり次第終了）","windowName":"住宅政策課","windowPhone":"054-221-1422","windowUrl":"https://www.city.shizuoka.lg.jp/412_000031.html","noSubsidyNote":null,"notes":"政令指定都市。特定空家等に指定された場合は上限100万円。事前に担当窓口へ要相談。※要確認"},"garbage":{"hasService":null,"applicationUrl":null,"applicationPhone":null,"notes":null}},
  {"prefId":"shizuoka","cityId":"hamamatsu","cityName":"浜松市","prefName":"静岡県","mascot":null,"subsidy":{"hasSubsidy":true,"name":"浜松市空家等除却促進事業費補助金","maxAmount":"最大50万円（解体費用の1/3以内）","conditions":["昭和56年5月31日以前に建築済み又は建築確認済みであった空き家","令和3年12月31日以前に相続又は遺贈が発生していること","申請日から過去3年間空き家であること","相続人が所有者として登記されている一戸建て住宅","更地にする予定であること","浜松市税を完納していること","先着順（定員20名）"],"applicationPeriod":"令和7年4月21日～令和7年12月26日（先着20名）","windowName":"市民生活課","windowPhone":"053-457-2760","windowUrl":"https://www.city.hamamatsu.shizuoka.jp/simink/akiya/akiyahozixyo.html","noSubsidyNote":null,"notes":"政令指定都市。定員20名の先着順。事前相談（郵送）が必須。"},"garbage":{"hasService":null,"applicationUrl":null,"applicationPhone":null,"notes":null}},
  {"prefId":"shizuoka","cityId":"numazu","cityName":"沼津市","prefName":"静岡県","mascot":null,"subsidy":{"hasSubsidy":true,"name":"沼津市空家等除却事業","maxAmount":"最大80万円（補助対象経費と標準除却費のうち少ない額の80%以内）","conditions":["1年以上空き家となっている住宅","老朽化が著しく倒壊等の危険がある状態","空き家の所有者（個人）またはその相続人","市税を滞納していないこと","補助金交付決定後に工事着手すること"],"applicationPeriod":"令和7年度（予算がなくなり次第終了）","windowName":"都市計画課","windowPhone":"055-934-4790","windowUrl":"https://www.city.numazu.shizuoka.jp/kurashi/sumai/akiya/jyokyaku.htm","noSubsidyNote":null,"notes":null},"garbage":{"hasService":null,"applicationUrl":null,"applicationPhone":null,"notes":null}},
  {"prefId":"shizuoka","cityId":"atami","cityName":"熱海市","prefName":"静岡県","mascot":null,"subsidy":{"hasSubsidy":true,"name":"老朽危険空家除却事業","maxAmount":"最大80万円（対象経費の4/5以内）","conditions":["老朽化が著しく危険な空き家","空き家の所有者（個人）またはその相続人","市税を滞納していないこと","補助金交付決定後に工事着手すること"],"applicationPeriod":"令和7年度（予算がなくなり次第終了）","windowName":"まちづくり課","windowPhone":"0557-86-6267","windowUrl":"https://www.city.atami.lg.jp/kurashi/sumai/1005144/1005902.html","noSubsidyNote":null,"notes":null},"garbage":{"hasService":null,"applicationUrl":null,"applicationPhone":null,"notes":null}},
  {"prefId":"shizuoka","cityId":"mishima","cityName":"三島市","prefName":"静岡県","mascot":null,"subsidy":{"hasSubsidy":false,"name":null,"maxAmount":null,"conditions":[],"applicationPeriod":null,"windowName":"建築住宅課 三島住まい推進室","windowPhone":"055-983-2660","windowUrl":"https://www.city.mishima.shizuoka.jp/ipn047844.html","noSubsidyNote":"三島市では現在、空き家解体を対象とした独自の補助金制度は設けられていません。空き家に関するご相談は建築住宅課三島住まい推進室にお問い合わせください。","notes":"公式サイトの補助金一覧および空き家サポート総合サイトに解体補助金の記載なし。"},"garbage":{"hasService":null,"applicationUrl":null,"applicationPhone":null,"notes":null}},
  {"prefId":"shizuoka","cityId":"ito","cityName":"伊東市","prefName":"静岡県","mascot":null,"subsidy":{"hasSubsidy":true,"name":"廃屋解体・撤去補助金","maxAmount":"最大30万円（補助対象費用の1/2以内）","conditions":["老朽化が著しく倒壊等の危険がある空き家（廃屋）","空き家の所有者（個人）またはその相続人","市税を滞納していないこと","補助金交付決定後に工事着手すること"],"applicationPeriod":"令和7年度（予算がなくなり次第終了）","windowName":"都市計画課","windowPhone":"0557-36-3312","windowUrl":"https://www.city.ito.shizuoka.jp/gyosei/soshikikarasagasu/toshikeikakuka/toshikeikaku/keikann/2527.html","noSubsidyNote":null,"notes":null},"garbage":{"hasService":null,"applicationUrl":null,"applicationPhone":null,"notes":null}},
  {"prefId":"shizuoka","cityId":"shimada","cityName":"島田市","prefName":"静岡県","mascot":null,"subsidy":{"hasSubsidy":true,"name":"島田市空き家解体事業費補助金","maxAmount":"最大30万円（解体費用の23%以内）※相続後3年以内は最大50万円","conditions":["昭和56年5月31日以前に建築された木造一戸建て住宅","空き家の所有者またはその相続人","市内の解体事業者が施工すること","市税を滞納していないこと","補助金交付決定後に工事着手すること"],"applicationPeriod":"令和7年度（予算がなくなり次第終了）","windowName":"まちづくり課","windowPhone":"0547-36-7194","windowUrl":"https://www.city.shimada.shizuoka.jp/kurashi-docs/445924540.html","noSubsidyNote":null,"notes":"被相続人の死亡日から3年以内に解体完了の場合は上限50万円に増額。"},"garbage":{"hasService":null,"applicationUrl":null,"applicationPhone":null,"notes":null}},
  {"prefId":"shizuoka","cityId":"fuji","cityName":"富士市","prefName":"静岡県","mascot":null,"subsidy":{"hasSubsidy":true,"name":"富士市危険空家除却促進補助金","maxAmount":"最大30万円（解体費用の1/2以内）※住民税非課税世帯は最大50万円","conditions":["特定空家等に認定された保安上危険な空き家、または昭和56年5月31日以前に建築され周辺に危険を及ぼすおそれのある空き家","空き家の所有者（個人）またはその相続人","市税を滞納していないこと","補助金交付決定後に工事着手すること"],"applicationPeriod":"令和7年4月1日～令和9年3月31日","windowName":"住宅政策課","windowPhone":"0545-55-2814","windowUrl":"https://www.city.fuji.shizuoka.jp/kurashi/c0309/akiyajyokyakuhojyo.html","noSubsidyNote":null,"notes":"住民税非課税世帯は上限額が20万円加算され最大50万円。事前調査申出書の提出が必要。"},"garbage":{"hasService":null,"applicationUrl":null,"applicationPhone":null,"notes":null}},
  {"prefId":"shizuoka","cityId":"iwata","cityName":"磐田市","prefName":"静岡県","mascot":null,"subsidy":{"hasSubsidy":true,"name":"磐田市危険空き家等除却事業費補助金","maxAmount":"最大50万円（対象工事費の1/2以内）","conditions":["老朽化が著しく倒壊等の危険がある空き家","空き家の所有者（個人）またはその相続人","市税を滞納していないこと","補助金交付決定後に工事着手すること"],"applicationPeriod":"令和7年度（予算がなくなり次第終了）","windowName":"都市整備課","windowPhone":"0538-37-4887","windowUrl":"https://www.city.iwata.shizuoka.jp/kurashi_tetsuzuki/juutaku_pet_seikatsu/1010112/1001515.html","noSubsidyNote":null,"notes":null},"garbage":{"hasService":null,"applicationUrl":null,"applicationPhone":null,"notes":null}},
  {"prefId":"shizuoka","cityId":"yaizu","cityName":"焼津市","prefName":"静岡県","mascot":null,"subsidy":{"hasSubsidy":true,"name":"焼津市空き家除却事業補助金","maxAmount":"最大30万円（補助対象経費の1/3以内）","conditions":["老朽化が著しく倒壊等の危険がある空き家","空き家の所有者（個人）またはその相続人","市税を滞納していないこと","補助金交付決定後に工事着手すること"],"applicationPeriod":"令和7年度（予算がなくなり次第終了）","windowName":"建築住宅課","windowPhone":"054-626-1208","windowUrl":"https://www.city.yaizu.lg.jp/life/sumai-kenchiku/akiya/akiya-hojyo.html","noSubsidyNote":null,"notes":null},"garbage":{"hasService":null,"applicationUrl":null,"applicationPhone":null,"notes":null}},
  {"prefId":"shizuoka","cityId":"kakegawa","cityName":"掛川市","prefName":"静岡県","mascot":null,"subsidy":{"hasSubsidy":true,"name":"掛川市空き家除却事業費補助金","maxAmount":"最大50万円（定額）","conditions":["老朽化が著しく危険な空き家","空き家の所有者（個人）またはその相続人","市税を滞納していないこと","補助金交付決定後に工事着手すること"],"applicationPeriod":"令和7年度（予算がなくなり次第終了）","windowName":"建設政策課","windowPhone":"0537-21-1271","windowUrl":"https://www.city.kakegawa.shizuoka.jp/kurashi/sumai/1003936.html","noSubsidyNote":null,"notes":"定額50万円（工事費の実額が50万円未満の場合はその額）。詳細は公式サイトで最新情報を確認のこと。"},"garbage":{"hasService":null,"applicationUrl":null,"applicationPhone":null,"notes":null}},
  {"prefId":"shizuoka","cityId":"fujieda","cityName":"藤枝市","prefName":"静岡県","mascot":null,"subsidy":{"hasSubsidy":true,"name":"空き家解体・除却事業費補助金","maxAmount":"最大30万円（工事費の23%以内）※相続後3年以内は最大50万円","conditions":["1年以上使用されていない木造住宅","昭和56年5月31日以前に建築された空き家","空き家の所有者（個人）またはその相続人","市税を滞納していないこと","補助金交付決定後に工事着手すること"],"applicationPeriod":"令和7年度（予算がなくなり次第終了）","windowName":"都市建設部建築住宅課","windowPhone":"054-643-3277","windowUrl":"https://www.city.fujieda.shizuoka.jp/soshiki/toshikensetsu/akiya/gyomu/hojyokin/1527064532268.html","noSubsidyNote":null,"notes":"被相続人の死亡日から3年以内に解体完了の場合は上限50万円。Search Consoleで上位表示中のため公式サイトで最新情報を要確認。"},"garbage":{"hasService":null,"applicationUrl":null,"applicationPhone":null,"notes":null}},
  {"prefId":"shizuoka","cityId":"gotemba","cityName":"御殿場市","prefName":"静岡県","mascot":null,"subsidy":{"hasSubsidy":true,"name":"空き家活用等支援事業費補助金（除却）","maxAmount":"最大50万円（工事費の1/3以内）※中学生未満の子がいる移住世帯は最大80万円","conditions":["老朽化が著しく危険な空き家","1年以上空き家であること","空き家の所有者（個人）またはその相続人","市税を滞納していないこと","補助金交付決定後に工事着手すること"],"applicationPeriod":"令和7年度（予算がなくなり次第終了）","windowName":"建設水道部都市整備課","windowPhone":"0550-82-4517","windowUrl":"https://www.city.gotemba.lg.jp/kurashi/b-7/b-7-5/12230.html","noSubsidyNote":null,"notes":"中学生未満の子がいる移住世帯は上限80万円に増額。"},"garbage":{"hasService":null,"applicationUrl":null,"applicationPhone":null,"notes":null}},
  {"prefId":"shizuoka","cityId":"fukuroi","cityName":"袋井市","prefName":"静岡県","mascot":null,"subsidy":{"hasSubsidy":true,"name":"袋井市空き家跡地利用のための空き家除却支援事業費補助金","maxAmount":"詳細は窓口にお問い合わせください","conditions":["市内の空き家を除却し、跡地を居住環境の改善または地域活性化のために活用すること","空き家の所有者（個人）またはその相続人","市税を滞納していないこと","補助金交付決定後に工事着手すること"],"applicationPeriod":"令和7年度（予算がなくなり次第終了）","windowName":"ふくろいすまいの相談センター（建築住宅課）","windowPhone":"0538-44-3321","windowUrl":"https://www.city.fukuroi.shizuoka.jp/soshiki/53/sumainosoudann/1587967767606.html","noSubsidyNote":null,"notes":"※要確認：補助上限額・補助率が公式サイトに明記されていないため、事前に窓口にお問い合わせください。"},"garbage":{"hasService":null,"applicationUrl":null,"applicationPhone":null,"notes":null}},
  {"prefId":"shizuoka","cityId":"shimoda","cityName":"下田市","prefName":"静岡県","mascot":null,"subsidy":{"hasSubsidy":null,"name":null,"maxAmount":null,"conditions":[],"applicationPeriod":null,"windowName":null,"windowPhone":null,"windowUrl":null,"noSubsidyNote":null,"notes":"※要確認：公式サイトでの空き家解体補助金の記載が確認できませんでした。下田市建設水道部にお問い合わせください。"},"garbage":{"hasService":null,"applicationUrl":null,"applicationPhone":null,"notes":null}},
  {"prefId":"shizuoka","cityId":"susono","cityName":"裾野市","prefName":"静岡県","mascot":null,"subsidy":{"hasSubsidy":null,"name":null,"maxAmount":null,"conditions":[],"applicationPeriod":null,"windowName":null,"windowPhone":null,"windowUrl":null,"noSubsidyNote":null,"notes":"※要確認：公式サイトで空き家解体補助金の確認ができませんでした。裾野市建築住宅課にお問い合わせください。"},"garbage":{"hasService":null,"applicationUrl":null,"applicationPhone":null,"notes":null}},
  {"prefId":"shizuoka","cityId":"kosai","cityName":"湖西市","prefName":"静岡県","mascot":null,"subsidy":{"hasSubsidy":null,"name":null,"maxAmount":null,"conditions":[],"applicationPeriod":null,"windowName":null,"windowPhone":null,"windowUrl":null,"noSubsidyNote":null,"notes":"※要確認：国土交通省の空き家対策マップにて解体補助制度の記載なし。湖西市建設部都市計画課にお問い合わせください。"},"garbage":{"hasService":null,"applicationUrl":null,"applicationPhone":null,"notes":null}},
  {"prefId":"shizuoka","cityId":"izu","cityName":"伊豆市","prefName":"静岡県","mascot":null,"subsidy":{"hasSubsidy":true,"name":"伊豆市老朽空家等除却支援事業補助金","maxAmount":"最大50万円（対象経費の1/2以内）※市への寄付条件付きの場合は最大300万円","conditions":["老朽化が著しく危険な空き家","空き家の所有者（個人）またはその相続人","市税を滞納していないこと","補助金交付決定後に工事着手すること","市への土地寄付の場合は300万円まで補助"],"applicationPeriod":"令和7年度（予算がなくなり次第終了）","windowName":"都市計画課 土地対策スタッフ","windowPhone":"0558-83-5206","windowUrl":"https://www.city.izu.shizuoka.jp/soshiki/1024/3/871.html","noSubsidyNote":null,"notes":"空き家率が高く（約32.9%）空き家問題が深刻。敷地を市に寄付する場合は最大300万円に増額。解体後の固定資産税減免制度あり。"},"garbage":{"hasService":null,"applicationUrl":null,"applicationPhone":null,"notes":null}},
  {"prefId":"shizuoka","cityId":"omaezaki","cityName":"御前崎市","prefName":"静岡県","mascot":null,"subsidy":{"hasSubsidy":true,"name":"御前崎市危険空家除却事業費補助金","maxAmount":"最大60万円（対象経費の4/5以内）","conditions":["老朽化が著しく危険な空き家（不良住宅に相当するもの）","空き家の所有者（個人）またはその相続人","市税を滞納していないこと","補助金交付決定後に工事着手すること"],"applicationPeriod":"令和7年度（予算がなくなり次第終了）","windowName":"都市政策課","windowPhone":"0537-85-1178","windowUrl":"https://www.city.omaezaki.shizuoka.jp/soshiki/toshiseisaku/sumaitochi/sumai/akiya/kikennakiyatoujokyakujigyouhihojokinn.html","noSubsidyNote":null,"notes":null},"garbage":{"hasService":null,"applicationUrl":null,"applicationPhone":null,"notes":null}},
  {"prefId":"shizuoka","cityId":"kikugawa","cityName":"菊川市","prefName":"静岡県","mascot":null,"subsidy":{"hasSubsidy":true,"name":"空家等の除却（解体）補助制度","maxAmount":"最大30万円（解体工事費の23%以内）","conditions":["老朽化が著しく危険な空き家","昭和56年5月31日以前に建築された空き家","空き家の所有者（個人）またはその相続人","市税を滞納していないこと","補助金交付決定後に工事着手すること"],"applicationPeriod":"令和7年度（予算がなくなり次第終了）","windowName":"都市計画課","windowPhone":"0537-35-0948","windowUrl":"https://www.city.kikugawa.shizuoka.jp/toshikeikaku/jokyakuhojo.html","noSubsidyNote":null,"notes":"Search Consoleで上位表示中のため、公式サイトで令和7年度の最新情報を要確認。"},"garbage":{"hasService":null,"applicationUrl":null,"applicationPhone":null,"notes":null}},
  {"prefId":"shizuoka","cityId":"izunokuni","cityName":"伊豆の国市","prefName":"静岡県","mascot":null,"subsidy":{"hasSubsidy":null,"name":null,"maxAmount":null,"conditions":[],"applicationPeriod":null,"windowName":null,"windowPhone":null,"windowUrl":null,"noSubsidyNote":null,"notes":"※要確認：空き家解体補助金の確認ができませんでした。伊豆の国市建設部建築住宅課にお問い合わせください。"},"garbage":{"hasService":null,"applicationUrl":null,"applicationPhone":null,"notes":null}},
  {"prefId":"shizuoka","cityId":"makinohara","cityName":"牧之原市","prefName":"静岡県","mascot":null,"subsidy":{"hasSubsidy":null,"name":null,"maxAmount":null,"conditions":[],"applicationPeriod":null,"windowName":null,"windowPhone":null,"windowUrl":null,"noSubsidyNote":null,"notes":"※要確認：リフォーム補助・家財処理補助は確認済みだが、解体補助金の記載が確認できませんでした。牧之原市地域整備課にお問い合わせください。"},"garbage":{"hasService":null,"applicationUrl":null,"applicationPhone":null,"notes":null}},
  {"prefId":"shizuoka","cityId":"higashiizu","cityName":"東伊豆町","prefName":"静岡県","mascot":null,"subsidy":{"hasSubsidy":null,"name":null,"maxAmount":null,"conditions":[],"applicationPeriod":null,"windowName":null,"windowPhone":null,"windowUrl":null,"noSubsidyNote":null,"notes":"※要確認：公式サイトでは空き家バンク登録物件の改修支援・家財道具処分支援のみ確認。空き家解体（除却）補助金の存在は確認できませんでした。東伊豆町企画調整課へお問い合わせください。"},"garbage":{"hasService":null,"applicationUrl":null,"applicationPhone":null,"notes":null}},
  {"prefId":"shizuoka","cityId":"kawazu","cityName":"河津町","prefName":"静岡県","mascot":null,"subsidy":{"hasSubsidy":null,"name":null,"maxAmount":null,"conditions":[],"applicationPeriod":null,"windowName":null,"windowPhone":null,"windowUrl":null,"noSubsidyNote":null,"notes":"※要確認：伊豆半島の別荘・空き家問題が深刻な地域。河津町役場建設課にお問い合わせください。"},"garbage":{"hasService":null,"applicationUrl":null,"applicationPhone":null,"notes":null}},
  {"prefId":"shizuoka","cityId":"minamiizu","cityName":"南伊豆町","prefName":"静岡県","mascot":null,"subsidy":{"hasSubsidy":null,"name":null,"maxAmount":null,"conditions":[],"applicationPeriod":null,"windowName":null,"windowPhone":null,"windowUrl":null,"noSubsidyNote":null,"notes":"※要確認：伊豆半島の別荘・空き家問題が深刻な地域。南伊豆町役場建設課にお問い合わせください。"},"garbage":{"hasService":null,"applicationUrl":null,"applicationPhone":null,"notes":null}},
  {"prefId":"shizuoka","cityId":"matsuzaki","cityName":"松崎町","prefName":"静岡県","mascot":null,"subsidy":{"hasSubsidy":null,"name":null,"maxAmount":null,"conditions":[],"applicationPeriod":null,"windowName":null,"windowPhone":null,"windowUrl":null,"noSubsidyNote":null,"notes":"※要確認：伊豆半島の別荘・空き家問題が深刻な地域。松崎町役場建設課にお問い合わせください。"},"garbage":{"hasService":null,"applicationUrl":null,"applicationPhone":null,"notes":null}},
  {"prefId":"shizuoka","cityId":"nishiizu","cityName":"西伊豆町","prefName":"静岡県","mascot":null,"subsidy":{"hasSubsidy":null,"name":null,"maxAmount":null,"conditions":[],"applicationPeriod":null,"windowName":null,"windowPhone":null,"windowUrl":null,"noSubsidyNote":null,"notes":"※要確認：伊豆半島の別荘・空き家問題が深刻な地域。西伊豆町役場建設課にお問い合わせください。"},"garbage":{"hasService":null,"applicationUrl":null,"applicationPhone":null,"notes":null}},
  {"prefId":"shizuoka","cityId":"kannami","cityName":"函南町","prefName":"静岡県","mascot":null,"subsidy":{"hasSubsidy":null,"name":null,"maxAmount":null,"conditions":[],"applicationPeriod":null,"windowName":null,"windowPhone":null,"windowUrl":null,"noSubsidyNote":null,"notes":"※要確認：函南町役場建設課にお問い合わせください。"},"garbage":{"hasService":null,"applicationUrl":null,"applicationPhone":null,"notes":null}},
  {"prefId":"shizuoka","cityId":"shimizucho","cityName":"清水町","prefName":"静岡県","mascot":null,"subsidy":{"hasSubsidy":null,"name":null,"maxAmount":null,"conditions":[],"applicationPeriod":null,"windowName":null,"windowPhone":null,"windowUrl":null,"noSubsidyNote":null,"notes":"※要確認：清水町役場建設課にお問い合わせください。"},"garbage":{"hasService":null,"applicationUrl":null,"applicationPhone":null,"notes":null}},
  {"prefId":"shizuoka","cityId":"nagaizumi","cityName":"長泉町","prefName":"静岡県","mascot":null,"subsidy":{"hasSubsidy":null,"name":null,"maxAmount":null,"conditions":[],"applicationPeriod":null,"windowName":null,"windowPhone":null,"windowUrl":null,"noSubsidyNote":null,"notes":"※要確認：長泉町役場建設課にお問い合わせください。"},"garbage":{"hasService":null,"applicationUrl":null,"applicationPhone":null,"notes":null}},
  {"prefId":"shizuoka","cityId":"oyama","cityName":"小山町","prefName":"静岡県","mascot":null,"subsidy":{"hasSubsidy":null,"name":null,"maxAmount":null,"conditions":[],"applicationPeriod":null,"windowName":null,"windowPhone":null,"windowUrl":null,"noSubsidyNote":null,"notes":"※要確認：小山町役場建設課にお問い合わせください。"},"garbage":{"hasService":null,"applicationUrl":null,"applicationPhone":null,"notes":null}},
  {"prefId":"shizuoka","cityId":"yoshida","cityName":"吉田町","prefName":"静岡県","mascot":null,"subsidy":{"hasSubsidy":null,"name":null,"maxAmount":null,"conditions":[],"applicationPeriod":null,"windowName":null,"windowPhone":null,"windowUrl":null,"noSubsidyNote":null,"notes":"※要確認：吉田町役場建設課にお問い合わせください。"},"garbage":{"hasService":null,"applicationUrl":null,"applicationPhone":null,"notes":null}},
  {"prefId":"shizuoka","cityId":"mori","cityName":"森町","prefName":"静岡県","mascot":null,"subsidy":{"hasSubsidy":null,"name":null,"maxAmount":null,"conditions":[],"applicationPeriod":null,"windowName":null,"windowPhone":null,"windowUrl":null,"noSubsidyNote":null,"notes":"※要確認：森町役場建設課にお問い合わせください。"},"garbage":{"hasService":null,"applicationUrl":null,"applicationPhone":null,"notes":null}}
]
